CHANGES.rst
LICENSE
MANIFEST.in
README.rst
setup.cfg
setup.py
FluidNexus/BuildManpage.py
FluidNexus/Cmdline.py
FluidNexus/Database.py
FluidNexus/FluidNexus_pb2.py
FluidNexus/GUI.py
FluidNexus/Log.py
FluidNexus/MultipartPostHandlerUnicode.py
FluidNexus/Networking.py
FluidNexus/__init__.py
FluidNexus/version.py
FluidNexus/ui/FluidNexusAbout.ui
FluidNexus/ui/FluidNexusAboutUI.py
FluidNexus/ui/FluidNexusDesktop.ui
FluidNexus/ui/FluidNexusDesktopUI.py
FluidNexus/ui/FluidNexusHelp.ui
FluidNexus/ui/FluidNexusHelpUI.py
FluidNexus/ui/FluidNexusNewMessage.ui
FluidNexus/ui/FluidNexusNewMessageUI.py
FluidNexus/ui/FluidNexusPreferences.ui
FluidNexus/ui/FluidNexusPreferencesUI.py
FluidNexus/ui/FluidNexus_rc.py
FluidNexus/ui/__init__.py
FluidNexus/ui/res/FluidNexus.qrc
FluidNexus/ui/res/icons/fluid_nexus_icon-16x16-4.png
FluidNexus/ui/res/icons/fluid_nexus_icon-16x16-8.png
FluidNexus/ui/res/icons/fluid_nexus_icon-16x16.png
FluidNexus/ui/res/icons/fluid_nexus_icon-32x32-4.png
FluidNexus/ui/res/icons/fluid_nexus_icon-32x32-8.png
FluidNexus/ui/res/icons/fluid_nexus_icon-32x32.png
FluidNexus/ui/res/icons/fluid_nexus_icon-48x48-4.png
FluidNexus/ui/res/icons/fluid_nexus_icon-48x48-8.png
FluidNexus/ui/res/icons/fluid_nexus_icon-48x48.png
FluidNexus/ui/res/icons/fluid_nexus_icon-64x64.png
FluidNexus/ui/res/icons/fluid_nexus_icon.ico
FluidNexus/ui/res/icons/fluid_nexus_icon.png
FluidNexus/ui/res/icons/fluid_nexus_icon.xpm
FluidNexus/ui/res/icons/32x32/attachment_icon.png
FluidNexus/ui/res/icons/32x32/menu_add.png
FluidNexus/ui/res/icons/32x32/menu_all.png
FluidNexus/ui/res/icons/32x32/menu_blacklist.png
FluidNexus/ui/res/icons/32x32/menu_delete.png
FluidNexus/ui/res/icons/32x32/menu_edit.png
FluidNexus/ui/res/icons/32x32/menu_enable_outgoing.png
FluidNexus/ui/res/icons/32x32/menu_help.png
FluidNexus/ui/res/icons/32x32/menu_high_priority.png
FluidNexus/ui/res/icons/32x32/menu_outgoing.png
FluidNexus/ui/res/icons/32x32/menu_preferences.png
FluidNexus/ui/res/icons/32x32/menu_public.png
fluid_nexus.egg-info/PKG-INFO
fluid_nexus.egg-info/SOURCES.txt
fluid_nexus.egg-info/dependency_links.txt
fluid_nexus.egg-info/not-zip-safe
fluid_nexus.egg-info/requires.txt
fluid_nexus.egg-info/top_level.txt
