Metadata-Version: 1.0
Name: fluid-nexus
Version: 0.3.1
Summary: PyQt4 application that enables one to share messages and data independent of centralized data networks
Home-page: http://fluidnexus.net
Author: Nicholas Knouf
Author-email: fluidnexus@fluidnexus.net
License: UNKNOWN
Download-URL: http://fluidnexus.net/download
Keywords: ad-hoc networking,activism,bluetooth,zeroconf,communication
Platform: UNKNOWN
Classifier: Development Status :: 3 - Alpha
Classifier: Environment :: X11 Applications :: Qt
Classifier: Environment :: Win32 (MS Windows)
Classifier: Intended Audience :: End Users/Desktop
Classifier: License :: OSI Approved :: GNU General Public License (GPL)
Classifier: Operating System :: Microsoft :: Windows
Classifier: Operating System :: POSIX :: Linux
Classifier: Programming Language :: Python
Classifier: Topic :: Artistic Software
Classifier: Topic :: Communications
